wellgui/__init__.py
wellgui/app.py
wellgui/curve_types.py
wellgui/exceptions.py
wellgui-0.1.dist-info/LICENSE
wellgui-0.1.dist-info/METADATA
wellgui-0.1.dist-info/WHEEL
wellgui-0.1.dist-info/entry_points.txt
wellgui-0.1.dist-info/top_level.txt
wellgui-0.1.dist-info/RECORD
