Metadata-Version: 2.1
Name: wellgui
Version: 0.1
Summary: Graphical application for well logs
Author-email: Kent Inverarity <kinverarity@hotmail.com>
Project-URL: Homepage, https://github.com/kinverarity1/wellgui
Project-URL: Bug Tracker, https://github.com/kinverarity1/wellgui/issues
Keywords: science,geophysics
Classifier: Development Status :: 4 - Beta
Classifier: Environment :: Console
Classifier: Intended Audience :: Customer Service
Classifier: Intended Audience :: Developers
Classifier: Intended Audience :: Education
Classifier: Intended Audience :: End Users/Desktop
Classifier: Intended Audience :: Other Audience
Classifier: Intended Audience :: Science/Research
Classifier: Natural Language :: English
Classifier: Operating System :: OS Independent
Classifier: Programming Language :: Python :: 2.6
Classifier: Programming Language :: Python :: 2.7
Classifier: Programming Language :: Python :: 3
Classifier: Programming Language :: Python :: 3.2
Classifier: Programming Language :: Python :: 3.3
Classifier: Programming Language :: Python :: 3.4
Classifier: Topic :: Scientific/Engineering
Classifier: Topic :: System :: Filesystems
Classifier: Topic :: Scientific/Engineering :: Information Analysis
Requires-Python: >=3.7
License-File: LICENSE
Requires-Dist: pandas
Requires-Dist: numpy
Requires-Dist: PySide6
Requires-Dist: pyqtgraph
Requires-Dist: lasio
Provides-Extra: dev
Requires-Dist: pytest (>=3.6) ; extra == 'dev'
Requires-Dist: pytest-cov ; extra == 'dev'
Requires-Dist: coverage ; extra == 'dev'
Requires-Dist: codecov ; extra == 'dev'
Requires-Dist: pytest-benchmark ; extra == 'dev'
Requires-Dist: black ; extra == 'dev'
